LICENSE
README.md
setup.py
phenoai/__init__.py
phenoai/ainalyses.py
phenoai/client.py
phenoai/containers.py
phenoai/estimators.py
phenoai/exceptions.py
phenoai/io.py
phenoai/logger.py
phenoai/maker.py
phenoai/phenoai.py
phenoai/splash.py
phenoai/updatechecker.py
phenoai/utils.py
phenoai.egg-info/PKG-INFO
phenoai.egg-info/SOURCES.txt
phenoai.egg-info/dependency_links.txt
phenoai.egg-info/requires.txt
phenoai.egg-info/top_level.txt