Metadata-Version: 2.1
Name: phenoai
Version: 0.1.3
Summary: Machine Learning interface for High Energy Physics Phenomenology
Home-page: http://hef.ru.nl/~bstienen/phenoai
Author: Bob Stienen
Author-email: b.stienen@science.ru.nl
License: MIT
Keywords: high energy physics machine learning phenomenology limits exclusion likleihood likelihoods
Platform: UNKNOWN
Classifier: Development Status :: 4 - Beta
Classifier: Programming Language :: Python :: 3
Classifier: Intended Audience :: Science/Research
Classifier: License :: OSI Approved :: MIT License
Classifier: Natural Language :: English
Classifier: Topic :: Scientific/Engineering :: Physics
Classifier: Topic :: Scientific/Engineering :: Artificial Intelligence
